// class version 50.0 (50)
// access flags 0x401
public abstract class TTransporterTile$$6$class {


  // access flags 0x9
  public static $init$(LTTransporterTile$$6;)V
    RETURN
    MAXSTACK = 1
    MAXLOCALS = 1

  // access flags 0x9
  public static bindPart(LTTransporterTile$$6;Lcodechicken/multipart/TMultiPart;)V
    ALOAD 0
    ALOAD 1
    INVOKEINTERFACE TTransporterTile$$6.TTransporterTile$$6$$super$bindPart (Lcodechicken/multipart/TMultiPart;)V
    ALOAD 1
    INSTANCEOF mekanism/common/base/ITransporterTile
    IFEQ L0
    ALOAD 0
    ALOAD 1
    CHECKCAST mekanism/common/base/ITransporterTile
    INVOKEINTERFACE TTransporterTile$$6.TTransporterTile$$6$$impl_$eq (Lmekanism/common/base/ITransporterTile;)V
   L0
   FRAME FULL [TTransporterTile$$6 codechicken/multipart/TMultiPart] []
    RETURN
    MAXSTACK = 2
    MAXLOCALS = 2

  // access flags 0x9
  public static partRemoved(LTTransporterTile$$6;Lcodechicken/multipart/TMultiPart;I)V
    ALOAD 0
    ALOAD 1
    ILOAD 2
    INVOKEINTERFACE TTransporterTile$$6.TTransporterTile$$6$$super$partRemoved (Lcodechicken/multipart/TMultiPart;I)V
    ALOAD 1
    ALOAD 0
    INVOKEINTERFACE TTransporterTile$$6.TTransporterTile$$6$$impl ()Lmekanism/common/base/ITransporterTile;
    IF_ACMPNE L0
    ALOAD 0
    ACONST_NULL
    INVOKEINTERFACE TTransporterTile$$6.TTransporterTile$$6$$impl_$eq (Lmekanism/common/base/ITransporterTile;)V
   L0
   FRAME FULL [TTransporterTile$$6 codechicken/multipart/TMultiPart I] []
    RETURN
    MAXSTACK = 3
    MAXLOCALS = 3

  // access flags 0x9
  public static canAddPart(LTTransporterTile$$6;Lcodechicken/multipart/TMultiPart;)Z
    ALOAD 0
    INVOKEINTERFACE TTransporterTile$$6.TTransporterTile$$6$$impl ()Lmekanism/common/base/ITransporterTile;
    IFNULL L0
    ALOAD 1
    INSTANCEOF mekanism/common/base/ITransporterTile
    IFEQ L0
    ICONST_0
    IRETURN
   L0
   FRAME FULL [TTransporterTile$$6 codechicken/multipart/TMultiPart] []
    ALOAD 0
    ALOAD 1
    INVOKEINTERFACE TTransporterTile$$6.TTransporterTile$$6$$super$canAddPart (Lcodechicken/multipart/TMultiPart;)Z
    IRETURN
    MAXSTACK = 2
    MAXLOCALS = 2

  // access flags 0x9
  public static getTransmitter(LTTransporterTile$$6;)Lmekanism/common/base/ILogisticalTransporter;
    ALOAD 0
    INVOKEINTERFACE TTransporterTile$$6.TTransporterTile$$6$$impl ()Lmekanism/common/base/ITransporterTile;
    INVOKEINTERFACE mekanism/common/base/ITransporterTile.getTransmitter ()Lmekanism/common/base/ILogisticalTransporter;
    ARETURN
    MAXSTACK = 1
    MAXLOCALS = 1

  // access flags 0x9
  public static getTransmitter(LTTransporterTile$$6;)Lmekanism/api/transmitters/IGridTransmitter;
    ALOAD 0
    INVOKEINTERFACE TTransporterTile$$6.TTransporterTile$$6$$impl ()Lmekanism/common/base/ITransporterTile;
    INVOKEINTERFACE mekanism/common/base/ITransporterTile.getTransmitter ()Lmekanism/api/transmitters/IGridTransmitter;
    ARETURN
    MAXSTACK = 1
    MAXLOCALS = 1

  // access flags 0x9
  public static canConnectMutual(LTTransporterTile$$6;Lnet/minecraftforge/common/util/ForgeDirection;)Z
    ALOAD 0
    INVOKEINTERFACE TTransporterTile$$6.TTransporterTile$$6$$impl ()Lmekanism/common/base/ITransporterTile;
    ALOAD 1
    INVOKEINTERFACE mekanism/common/base/ITransporterTile.canConnectMutual (Lnet/minecraftforge/common/util/ForgeDirection;)Z
    IRETURN
    MAXSTACK = 2
    MAXLOCALS = 2

  // access flags 0x9
  public static canConnect(LTTransporterTile$$6;Lnet/minecraftforge/common/util/ForgeDirection;)Z
    ALOAD 0
    INVOKEINTERFACE TTransporterTile$$6.TTransporterTile$$6$$impl ()Lmekanism/common/base/ITransporterTile;
    ALOAD 1
    INVOKEINTERFACE mekanism/common/base/ITransporterTile.canConnect (Lnet/minecraftforge/common/util/ForgeDirection;)Z
    IRETURN
    MAXSTACK = 2
    MAXLOCALS = 2

  // access flags 0x9
  public static copyFrom(LTTransporterTile$$6;Lcodechicken/multipart/TileMultipart;)V
    ALOAD 0
    ALOAD 1
    INVOKEINTERFACE TTransporterTile$$6.TTransporterTile$$6$$super$copyFrom (Lcodechicken/multipart/TileMultipart;)V
    ALOAD 1
    INSTANCEOF TTransporterTile$$6
    IFEQ L0
    ALOAD 0
    ALOAD 1
    INVOKEINTERFACE TTransporterTile$$6.TTransporterTile$$6$$impl ()Lmekanism/common/base/ITransporterTile;
    INVOKEINTERFACE TTransporterTile$$6.TTransporterTile$$6$$impl_$eq (Lmekanism/common/base/ITransporterTile;)V
   L0
    RETURN
    MAXSTACK = 2
    MAXLOCALS = 2
}
